accessor_stubs/__init__.py
accessor_stubs/_registrar.py
accessor_stubs/versions.json
xarray-stubs/py.typed
xarray-stubs/core/__init__.pyi
xarray-stubs/core/dataarray.pyi
xarray-stubs/core/dataset.pyi
accessor_stubs-0.0.1.dist-info/METADATA
accessor_stubs-0.0.1.dist-info/WHEEL
accessor_stubs-0.0.1.dist-info/licenses/LICENSE
accessor_stubs-0.0.1.dist-info/RECORD
