Metadata-Version: 2.3
Name: accessor_stubs
Version: 0.0.1
Summary: stubgen for xarray and pandas accessors
Author-email: Constantine Karos <ckaros@outlook.com>
License: ?
License-File: LICENSE
Keywords: accessors,pandas,xarray
Classifier: Programming Language :: Python :: 3
Classifier: Programming Language :: Python :: 3.9
Classifier: Programming Language :: Python :: 3.10
Classifier: Programming Language :: Python :: 3.11
Classifier: Programming Language :: Python :: 3.12
Requires-Python: >=3.9
Requires-Dist: mypy
Requires-Dist: pandas
Requires-Dist: xarray
Provides-Extra: dev
Requires-Dist: hatch; extra == 'dev'
